setup.cfg
setup.py
CustomFN/__init__.py
CustomFN/get_cosmetic.py
CustomFN/utils.py
CustomFN.egg-info/PKG-INFO
CustomFN.egg-info/SOURCES.txt
CustomFN.egg-info/dependency_links.txt
CustomFN.egg-info/requires.txt
CustomFN.egg-info/top_level.txt
CustomFN/events/__init__.py
CustomFN/events/friends.py
CustomFN/events/message.py
CustomFN/events/party.py
CustomFN/events/ready.py