Metadata-Version: 1.0
Name: CustomFN
Version: 1.7
Summary: Fortnite Bot
Home-page: https://github.com/JaniniRami07/CustomFN/archive/1.7.tar.gz
Author: UNKNOWN
Author-email: janinirami@tutanota.com
License: UNKNOWN
Platform: UNKNOWN
